Workbook

Sheet Portada
B2: Checklist de limpieza de una web WordPress infectada
B3: 77 comprobaciones en 8 fases, de la primera copia de seguridad a recuperar la reputación en Google.
B6: Tu dominio | C6: ayudawp.com | D6: Escríbelo sin www y sin https. Los enlaces de las hojas 4 y 5 se montan solos con lo que pongas aquí.
B9: Antes de empezar, cuatro cosas
B10: Esto se puede romper. | C10: Buena parte de la fase 3 y de la 4 consiste en borrar ficheros y tocar la base de datos. Si no has descargado antes la copia completa de la fase 1, no sigas.
B11: Limpiar no es lo mismo que arreglar. | C11: Si no encuentras por dónde entraron, la web se vuelve a infectar en días y te preguntarás qué hiciste mal. No hiciste nada mal: dejaste la puerta abierta.
B12: Vas a perder personalizaciones. | C12: Al reinstalar el tema y los plugins desaparece lo que estuviera metido a mano dentro de esos ficheros. Por eso se copia antes.
B13: Si hay datos personales, hay plazo legal. | C13: 72 horas para notificar a la Agencia Española de Protección de Datos desde que te enteras. Eso corre desde ya, no desde que termines de limpiar.
B15: Cómo se rellena
B16: Estado | C16: Pendiente · En marcha · Hecho · No aplica. Se elige de la lista de la celda.
B17: Riesgo | C17: Seguro, Con cuidado o Puede romper la web. Las rojas no se hacen con prisa ni sin copia previa.
B18: Aplica si | C18: Muchas comprobaciones solo tienen sentido en algunos casos. Filtra por esta columna y marca «No aplica» en lo que no sea tu caso.
B20: Una fila de ejemplo, para que se vea el formato:
B21: Comprobación | C21: Estado | D21: Fecha | E21: Notas
B22: Deja la carpeta de subidas sin un solo PHP | C22: Hecho | D22: 10/09/2026 | E22: Tres ficheros en uploads/2024/07, borrados y anotados
B25: Cómo vas
B26: Fase | C26: Comprobaciones | D26: Hechas | E26: No aplican | F26: Pendientes | G26: Avance
B27: 0. Antes de tocar nada | C27: =COUNTIF('2 Checklist'!$A:$A,$B27) -> 4 | D27: =COUNTIFS('2 Checklist'!$A:$A,$B27,'2 Checklist'!$G:$G,"Hecho") -> 0 | E27: =COUNTIFS('2 Checklist'!$A:$A,$B27,'2 Checklist'!$G:$G,"No aplica") -> 0 | F27: =$C27-$D27-$E27 -> 4 | G27: =IF($C27-$E27=0,1,$D27/($C27-$E27)) -> 0
B28: 1. Contener y guardar pruebas | C28: =COUNTIF('2 Checklist'!$A:$A,$B28) -> 11 | D28: =COUNTIFS('2 Checklist'!$A:$A,$B28,'2 Checklist'!$G:$G,"Hecho") -> 0 | E28: =COUNTIFS('2 Checklist'!$A:$A,$B28,'2 Checklist'!$G:$G,"No aplica") -> 0 | F28: =$C28-$D28-$E28 -> 11 | G28: =IF($C28-$E28=0,1,$D28/($C28-$E28)) -> 0
B29: 2. Averiguar qué ha pasado | C29: =COUNTIF('2 Checklist'!$A:$A,$B29) -> 7 | D29: =COUNTIFS('2 Checklist'!$A:$A,$B29,'2 Checklist'!$G:$G,"Hecho") -> 0 | E29: =COUNTIFS('2 Checklist'!$A:$A,$B29,'2 Checklist'!$G:$G,"No aplica") -> 0 | F29: =$C29-$D29-$E29 -> 7 | G29: =IF($C29-$E29=0,1,$D29/($C29-$E29)) -> 0
B30: 3. Limpiar los ficheros | C30: =COUNTIF('2 Checklist'!$A:$A,$B30) -> 10 | D30: =COUNTIFS('2 Checklist'!$A:$A,$B30,'2 Checklist'!$G:$G,"Hecho") -> 0 | E30: =COUNTIFS('2 Checklist'!$A:$A,$B30,'2 Checklist'!$G:$G,"No aplica") -> 0 | F30: =$C30-$D30-$E30 -> 10 | G30: =IF($C30-$E30=0,1,$D30/($C30-$E30)) -> 0
B31: 4. Limpiar la base de datos | C31: =COUNTIF('2 Checklist'!$A:$A,$B31) -> 10 | D31: =COUNTIFS('2 Checklist'!$A:$A,$B31,'2 Checklist'!$G:$G,"Hecho") -> 0 | E31: =COUNTIFS('2 Checklist'!$A:$A,$B31,'2 Checklist'!$G:$G,"No aplica") -> 0 | F31: =$C31-$D31-$E31 -> 10 | G31: =IF($C31-$E31=0,1,$D31/($C31-$E31)) -> 0
B32: 5. Cerrar la puerta | C32: =COUNTIF('2 Checklist'!$A:$A,$B32) -> 13 | D32: =COUNTIFS('2 Checklist'!$A:$A,$B32,'2 Checklist'!$G:$G,"Hecho") -> 0 | E32: =COUNTIFS('2 Checklist'!$A:$A,$B32,'2 Checklist'!$G:$G,"No aplica") -> 0 | F32: =$C32-$D32-$E32 -> 13 | G32: =IF($C32-$E32=0,1,$D32/($C32-$E32)) -> 0
B33: 6. Comprobar que está limpia | C33: =COUNTIF('2 Checklist'!$A:$A,$B33) -> 6 | D33: =COUNTIFS('2 Checklist'!$A:$A,$B33,'2 Checklist'!$G:$G,"Hecho") -> 0 | E33: =COUNTIFS('2 Checklist'!$A:$A,$B33,'2 Checklist'!$G:$G,"No aplica") -> 0 | F33: =$C33-$D33-$E33 -> 6 | G33: =IF($C33-$E33=0,1,$D33/($C33-$E33)) -> 0
B34: 7. Recuperar la reputación | C34: =COUNTIF('2 Checklist'!$A:$A,$B34) -> 16 | D34: =COUNTIFS('2 Checklist'!$A:$A,$B34,'2 Checklist'!$G:$G,"Hecho") -> 0 | E34: =COUNTIFS('2 Checklist'!$A:$A,$B34,'2 Checklist'!$G:$G,"No aplica") -> 0 | F34: =$C34-$D34-$E34 -> 16 | G34: =IF($C34-$E34=0,1,$D34/($C34-$E34)) -> 0
B35: Total | C35: =SUM(C27:C34) -> 77 | D35: =SUM(D27:D34) -> 0 | E35: =SUM(E27:E34) -> 0 | F35: =SUM(F27:F34) -> 77 | G35: =IF($C35-$E35=0,1,$D35/($C35-$E35)) -> 0
B38: De dónde sale esto
B39: Es el protocolo que seguimos en AyudaWP para limpiar una web infectada, recortado a lo que puede hacer el dueño de la web por su cuenta. Puedes usarlo y compartirlo. Si a mitad de camino ves que se te va de las manos, escríbenos antes de tocar más.
B41: Tutoriales y guías de WordPress | C41: =HYPERLINK("https://ayudawp.com","https://ayudawp.com") -> https://ayudawp.com
B42: Herramientas gratuitas | C42: =HYPERLINK("https://herramientas.ayudawp.com","https://herramientas.ayudawp.com") -> https://herramientas.ayudawp.com
B43: Limpieza de webs infectadas | C43: =HYPERLINK("https://servicios.ayudawp.com","https://servicios.ayudawp.com") -> https://servicios.ayudawp.com
B44: Mantenimiento mensual de WordPress | C44: =HYPERLINK("https://mantenimiento.ayudawp.com","https://mantenimiento.ayudawp.com") -> https://mantenimiento.ayudawp.com
B45: Vigilante, para que no vuelva a pasar | C45: =HYPERLINK("https://vigilante.works/","https://vigilante.works/") -> https://vigilante.works/
B47: Versión 1.0 · 2026-09-10 · ayudawp.com

Sheet 1 Antes de empezar
A1: Lo que necesitas tener a mano antes de empezar
A2: Reunir esto primero te ahorra parar la limpieza a mitad para buscar una contraseña.
A4: Grupo | B4: Qué necesitas | C4: Por qué | D4: ¿Lo tienes?
A5: Accesos | B5: Panel de hosting | C5: Panel de hosting con permiso para gestionar ficheros y copias. Si no tienes tú las claves, pídelas antes de empezar. | D5: Pendiente
B6: FTP o SFTP | C6: FTP o SFTP, mejor SFTP si tu hosting lo ofrece. | D6: Pendiente
B7: SSH | C7: SSH, si lo tienes. Acelera muchísimo el trabajo de buscar y comparar ficheros. | D7: Pendiente
B8: Base de datos | C8: Acceso a la base de datos por phpMyAdmin o Adminer, por si el panel no te lo da directo. | D8: Pendiente
B9: Gestor de DNS | C9: Gestor de DNS, para revisar los registros de correo sobre todo. | D9: Pendiente
B10: Registrador del dominio | C10: Registrador del dominio, solo si hay que tocar nameservers o te han secuestrado el dominio. | D10: Pendiente
B11: Google Search Console | C11: Google Search Console verificado. Sin esto no puedes pedir la revisión de seguridad, que es la única vía para quitar el aviso de Google. | D11: Pendiente
B12: Bing Webmaster Tools | C12: Bing Webmaster Tools, por la misma razón. | D12: Pendiente
B13: Correo del dominio | C13: Acceso al correo del dominio, para revisar cuentas y colas si hay spam saliente. | D13: Pendiente
B14: Cloudflare, CDN o WAF | C14: Cloudflare, CDN o cortafuegos, si tienes algo por delante. Condiciona lo que se ve desde fuera y hay cachés que purgar. | D14: Pendiente
B15: Pasarela de pago | C15: Pasarela de pago, si tienes tienda y te han avisado. | D15: Pendiente
B16: Sistema de copias | C16: El sistema de copias, sea plugin o del hosting, para ver qué hay y de qué fecha. | D16: Pendiente
B17: Un usuario administrador que sepas que es tuyo | C17: Y comprueba que no hay otros administradores que no reconozcas antes de fiarte de nada de lo que veas en el escritorio. | D17: Pendiente
A18: Información | B18: Qué han visto y desde cuándo | C18: Qué has visto y desde cuándo, con tus palabras. La fecha aproximada ayuda a acotar el resto. | D18: Pendiente
B19: Qué han tocado ya | C19: Qué has tocado ya. Media limpieza se complica por lo que se hizo antes de pararse a pensar, así que apúntalo sin reproches. | D19: Pendiente
B20: Avisos recibidos | C20: Avisos que hayas recibido de Google, del hosting, de la pasarela o de tus propios clientes. | D20: Pendiente
B21: Copias disponibles y de qué fecha | C21: Copias disponibles y de qué fecha, sobre todo si alguna es anterior al problema. | D21: Pendiente
B22: Quién tiene acceso y desde qué equipos | C22: Quién tiene acceso y desde qué equipos. Si entraron con una contraseña robada, el problema puede estar en un portátil. | D22: Pendiente
B23: Qué datos personales trata la web | C23: Qué datos personales trata la web. Es lo que decide si hay brecha que valorar y el plazo de 72 horas. | D23: Pendiente
B24: Otras webs en la misma cuenta | C24: Otras webs en la misma cuenta de hosting. | D24: Pendiente
B25: Persona de contacto y horario para parar la web | C25: Cuándo puedes parar la web sin cargarte el día. En una tienda, esto no se improvisa. | D25: Pendiente
B26: Pedidos y pagos del periodo afectado | C26: Pedidos y pagos del periodo afectado, si tienes tienda, para valorar si hubo captura de datos de pago. | D26: Pendiente
B27: Un ordenador del que te fíes | C27: Si el vector fueron credenciales robadas de un equipo con malware, limpiar la web desde ese mismo equipo es empezar la casa por el tejado. Pasa un antivirus antes. | D27: Pendiente

Sheet 2 Checklist
A1: El checklist
A2: Las fases van en orden y el orden importa. Filtra por «Aplica si» para quitarte de encima lo que no sea tu caso.
A4: Fase | B4: Nº | C4: Comprobación | D4: Cómo se hace | E4: Aplica si | F4: Riesgo | G4: Estado | H4: Fecha | I4: Notas
A5: 0. Antes de tocar nada | B5: 1 | C5: Piensa qué datos personales guarda tu web | D5: Clientes, pedidos, suscriptores del boletín, formularios de contacto, comentarios con su correo. Si hay algo de eso, los dos puntos siguientes te afectan. En una tienda la respuesta es que sí, siempre. | E5: Siempre | F5: Seguro | G5: Pendiente
A6: 0. Antes de tocar nada | B6: 2 | C6: Valora si tienes que notificar la brecha a la AEPD (RGPD art. 33) | D6: Si han podido acceder a datos personales, tienes 72 horas para notificarlo a la Agencia Española de Protección de Datos desde que te enteras. Que la web sea pequeña y tuya no te libra. Documenta la valoración y la decisión aunque decidas no notificar, porque lo que te van a pedir luego es el razonamiento. | E6: Si hay datos personales | F6: Seguro | G6: Pendiente
A7: 0. Antes de tocar nada | B7: 3 | C7: Decide si tienes que avisar también a los afectados (RGPD art. 34) | D7: Cuando el riesgo para las personas es alto, además de notificar a la Agencia hay que avisarlas a ellas. La decisión es tuya como responsable del tratamiento, no de quien te limpie la web. Si tienes asesoría de protección de datos, esta llamada es para ellos. | E7: Si hay datos personales | F7: Seguro | G7: Pendiente
A8: 0. Antes de tocar nada | B8: 4 | C8: Decide cuándo puedes parar la web y por cuánto tiempo | D8: Vas a tener que dejarla en mantenimiento un rato largo. Si vendes, mira antes tus horas buenas y avisa a quien atienda pedidos o teléfono. | E8: Siempre | F8: Seguro | G8: Pendiente
A9: 1. Contener y guardar pruebas | B9: 5 | C9: Haz la foto del estado inicial desde fuera | D9: Antes de tocar nada, pasa la web por los escáneres de la hoja «4 Comprobaciones online» y anota lo que salga en cada uno. Es tu punto de partida, y sin él no podrás demostrar después que la has arreglado. | E9: Siempre | F9: Seguro | G9: Pendiente
A10: 1. Contener y guardar pruebas | B10: 6 | C10: Haz capturas de todo lo que se vea mal | D10: La portada como la ve un visitante, el aviso de Google si lo hay, la pantalla de Search Console y los escáneres que marquen algo. Hazlas también desde el móvil, que muchas infecciones solo se ven ahí. | E10: Siempre | F10: Seguro | G10: Pendiente
A11: 1. Contener y guardar pruebas | B11: 7 | C11: Descarga una copia completa de la web infectada y guárdala aparte | D11: Ficheros y base de datos tal como están ahora, con el bicho dentro, bajados a tu ordenador o a un disco externo. No la borres al terminar. Si más adelante aparece algo, o alguien te pregunta qué pasó, es lo único que lo prueba. Anota la fecha. | E11: Siempre | F11: Seguro | G11: Pendiente
A12: 1. Contener y guardar pruebas | B12: 8 | C12: Mira qué copias de seguridad tienes y de qué fecha | D12: Las del hosting, las del plugin de copias y las que hayas descargado alguna vez. Lo que importa es si alguna es anterior al día en que empezó esto, porque eso decide el punto siguiente. | E12: Siempre | F12: Seguro | G12: Pendiente
A13: 1. Contener y guardar pruebas | B13: 9 | C13: Decide si restauras una copia limpia o limpias lo que hay | D13: Restaurar es más rápido y más seguro, pero pierdes todo lo publicado desde esa fecha y no cierra el agujero por el que entraron. Si restauras, tendrás que hacer igualmente las fases 5 y 6 o volverás a estar donde estabas. Anota por qué has elegido lo que has elegido. | E13: Siempre | F13: Seguro | G13: Pendiente
A14: 1. Contener y guardar pruebas | B14: 10 | C14: Pon la web en mantenimiento mientras trabajas | D14: Con un aviso claro y devolviendo un código 503, que es el que le dice a Google que la parada es temporal. Si dejas la web en pie mientras limpias, sigues repartiendo malware entre tus visitantes. | E14: Siempre | F14: Con cuidado | G14: Pendiente
A15: 1. Contener y guardar pruebas | B15: 11 | C15: Revisa el resto de webs de la misma cuenta de hosting | D15: El salto de una web a otra dentro de la misma cuenta es de lo más común que hay. Si tienes tres webs en el mismo alojamiento, tienes tres webs que revisar antes de dar nada por limpio. | E15: Si hay más webs en la misma cuenta | F15: Seguro | G15: Pendiente
A16: 1. Contener y guardar pruebas | B16: 12 | C16: Comprueba si tu dominio está enviando spam | D16: Mira la cola de correo en el panel del hosting y las cuentas con envíos que no cuadran. Si sale spam, córtalo antes de pedir que te saquen de ninguna lista negra. | E16: Siempre | F16: Seguro | G16: Pendiente
... A56: 5. Cerrar la puerta | B56: 52 | C56: Sustituye lo que ya no tenga mantenimiento | D56: Lo abandonado o retirado del repositorio no se va a actualizar nunca más, así que su próximo fallo de seguridad no lo va a arreglar nadie. | E56: Siempre | F56: Con cuidado | G56: Pendiente
A57: 5. Cerrar la puerta | B57: 53 | C57: Pon vigilancia de cambios en ficheros y de vulnerabilidades | D57: Es lo que te avisa la próxima vez antes de que se entere Google. Vigilante vigila los cambios en ficheros y las vulnerabilidades de lo que tienes instalado, y es gratuito. | E57: Siempre | F57: Seguro | G57: Pendiente | I57: =HYPERLINK("https://vigilante.works/","https://vigilante.works/") -> https://vigilante.works/
A58: 5. Cerrar la puerta | B58: 54 | C58: Comprueba que las copias funcionan y prueba a restaurar una | D58: Una copia que no has restaurado nunca no es una copia, es una carpeta. Prueba la restauración en un entorno de pruebas, no encima de la web buena. | E58: Siempre | F58: Seguro | G58: Pendiente
A59: 5. Cerrar la puerta | B59: 55 | C59: Revoca los accesos que ya no hagan falta | D59: El de quien te montó la web hace tres años, el de la agencia que ya no lleva nada, el usuario que creaste para una prueba. Cada acceso que sobra es una puerta más. | E59: Siempre | F59: Seguro | G59: Pendiente
A60: 6. Comprobar que está limpia | B60: 56 | C60: Repite las comprobaciones de fuera y compáralas con las del principio | D60: Las mismas de la hoja «4 Comprobaciones online», con la misma vara de medir. Lo que siga en rojo, o lo arreglas o sabes explicar por qué está así. | E60: Siempre | F60: Seguro | G60: Pendiente
A61: 6. Comprobar que está limpia | B61: 57 | C61: Vuelve a buscar los patrones de código | D61: La segunda pasada es la que encuentra lo que se quedó a medias. Si aparece algo que no estaba en la primera, es que sigue habiendo una vía abierta y hay que volver a la fase 2. | E61: Siempre | F61: Seguro | G61: Pendiente
A62: 6. Comprobar que está limpia | B62: 58 | C62: Haz las capturas del estado final | D62: Las mismas que hiciste al empezar, para poder ponerlas al lado y ver el antes y el después. | E62: Siempre | F62: Seguro | G62: Pendiente
A63: 6. Comprobar que está limpia | B63: 59 | C63: Espera 72 horas y vuelve a mirar | D63: Si vuelve, es que queda una puerta trasera o el agujero de entrada sigue abierto. No des el trabajo por terminado el mismo día que acabas. | E63: Siempre | F63: Seguro | G63: Pendiente
A64: 6. Comprobar que está limpia | B64: 60 | C64: Quita el modo mantenimiento y comprueba que la portada responde 200 | D64: Un 503 que se queda puesto se come el posicionamiento en pocos días. Comprueba también que has borrado el fichero de la página de aviso, que se olvida más de lo que parece. | E64: Siempre | F64: Con cuidado | G64: Pendiente
A65: 6. Comprobar que está limpia | B65: 61 | C65: Vuelve a poner tu código y comprueba que funciona | D65: Que la analítica registre visitas otra vez y que las verificaciones de propiedad sigan en pie. Comprobado de verdad, abriendo el panel, no dado por hecho. | E65: Siempre | F65: Seguro | G65: Pendiente
A66: 7. Recuperar la reputación | B66: 62 | C66: Pide la revisión de seguridad en Search Console | D66: En Seguridad y acciones manuales, Problemas de seguridad. Solo con la web ya limpia, porque un intento gastado con la web todavía sucia alarga la espera. | E66: Si Google marcó la web | F66: Seguro | G66: Pendiente
A67: 7. Recuperar la reputación | B67: 63 | C67: Confirma que el aviso de Google ha desaparecido, y anota la fecha | D67: En Search Console y en el informe de transparencia. Apunta el día, que es lo que le vas a decir a quien te escriba diciendo que le sale que tu web es peligrosa. | E67: Si Google marcó la web | F67: Seguro | G67: Pendiente
A68: 7. Recuperar la reputación | B68: 64 | C68: Pide la revisión en Bing Webmaster Tools | D68: Alimenta a otros buscadores y a algunos antivirus, así que no te lo saltes aunque Bing te traiga poco tráfico. | E68: Siempre | F68: Seguro | G68: Pendiente
A69: 7. Recuperar la reputación | B69: 65 | C69: Sucuri SiteCheck limpio, con captura | D69: Es el escáner que suelen mirar los clientes y del que beben bastantes otros. Si sigue marcando algo después de limpiar, es que queda algo: míralo antes de discutir con nadie. | E69: Siempre | F69: Seguro | G69: Pendiente
... A80: 7. Recuperar la reputación | B80: 76 | C80: Busca site:tudominio en Google hasta que no salga basura | D80: Y la variante con términos de spam, que la tienes montada en la hoja «4 Comprobaciones online». Mientras devuelva resultados, la retirada no ha terminado aunque la web ya esté limpia. | E80: Si hubo spam SEO | F80: Seguro | G80: Pendiente
A81: 7. Recuperar la reputación | B81: 77 | C81: Repite el análisis de seguridad y compáralo con el del principio | D81: La misma herramienta que pasaste al empezar, para ver el antes y el después con la misma vara de medir. | E81: Siempre | F81: Seguro | G81: Pendiente | I81: =HYPERLINK("https://herramientas.ayudawp.com/security-check/","https://herramientas.ayudawp.com/security-check/") -> https://herramientas.ayudawp.com/security-check/

Sheet 3 Diagnóstico
A1: Diagnóstico: qué mirar y cómo se mira
A2: Se pasa dos veces, al principio y al terminar, y se comparan las dos columnas. Un «Mal» que sigue igual después de limpiar es trabajo sin acabar.
A4: Grupo | B4: Comprobación | C4: Qué significa | D4: Cómo lo compruebas tú | E4: Gravedad | F4: Resultado | G4: Notas
A5: Cloaking y redirecciones | B5: ¿Sirve el mismo contenido a Googlebot que a un navegador? | C5: Si a Googlebot le enseña otra cosa, hay spam SEO inyectado. Es la comprobación que más veces destapa el problema. | D5: Con la Inspección de URL de Search Console, en «Ver página rastreada», comparas el HTML que ve Google con el que ves tú. También puedes cambiar el user-agent desde las herramientas de desarrollo del navegador. | E5: alta | F5: Sin comprobar
B6: ¿Sirve el mismo contenido en móvil que en escritorio? | C6: Muchas campañas redirigen solo en móvil, que es donde el dueño de la web casi nunca mira. | D6: Abre la web en el móvil con datos, no con tu wifi, y navega por varias páginas. Muchas campañas redirigen solo ahí. | E6: alta | F6: Sin comprobar
B7: ¿Se comporta igual llegando desde Google que directamente? | C7: El clásico: tú entras por tu marcador y ves la web perfecta, y quien llega desde Google acaba en otra parte. | D7: Busca tu web en Google y entra desde el resultado, no desde un marcador. Es la comprobación que más veces destapa el problema. | E7: alta | F7: Sin comprobar
B8: ¿Termina la navegación en el mismo dominio? | C8: Cadena de redirecciones que acaba en un dominio de terceros. | D8: Fíjate en la barra de direcciones después de cargar. Si acabas en otro dominio, tienes una cadena de redirecciones montada. | E8: alta | F8: Sin comprobar
A9: Contenido inyectado | B9: ¿Está el HTML libre de bloques codificados sospechosos? | C9: Cadenas base64 largas, eval o atob dentro del HTML servido. | D9: Mira el código fuente de la portada (Ctrl+U) y busca cadenas larguísimas de letras y números, o las palabras eval y atob. | E9: alta | F9: Sin comprobar
B10: ¿Todos los scripts vienen de dominios reconocibles? | C10: Scripts cargados desde dominios que no son ni el propio ni CDN conocidas. | D10: En el código fuente, revisa cada etiqueta script con src. Todo dominio que no sea el tuyo ni una CDN que reconozcas merece una mirada. | E10: alta | F10: Sin comprobar
B11: ¿Está libre de iframes ocultos? | C11: Iframes de 1 píxel o con display:none, clásico para distribuir malware. | D11: Busca la palabra iframe en el código fuente. Los de 1 píxel o con display:none no están ahí para nada bueno. | E11: alta | F11: Sin comprobar
B12: ¿Está libre de enlaces salientes de spam? | C12: Enlaces a farmacia, casino, réplicas o préstamos, muchas veces ocultos con CSS. | D12: Busca en el código fuente términos de farmacia, casino, réplicas o préstamos. Suelen ir escondidos con CSS, así que en pantalla no se ven. | E12: alta | F12: Sin comprobar
B13: ¿La búsqueda interna está limpia de términos de spam? | C13: Si el buscador de tu propia web devuelve resultados con palabras de spam, tienes contenido inyectado y publicado. | D13: Usa el buscador de tu propia web con esas mismas palabras. Si devuelve resultados, tienes contenido inyectado y publicado. | E13: alta | F13: Sin comprobar
B14: ¿El sitemap solo tiene URLs del negocio? | C14: URLs ajenas al negocio o un número de entradas que no cuadra. | D14: Abre tu sitemap.xml y mira si el número de URLs cuadra con lo que tienes publicado, y si hay direcciones que no reconoces. | E14: media | F14: Sin comprobar
B15: ¿El título y la descripción de la portada son los del negocio? | C15: Cuando cambian, o hay defacement o hay dopaje de SEO. | D15: Busca tu web en Google y mira el título y la descripción que salen. Cuando cambian, o hay defacement o hay dopaje de SEO. | E15: media | F15: Sin comprobar
A16: Superficie y ficheros | B16: ¿No responden rutas de puertas traseras conocidas? | C16: Se prueban nombres habituales de shells subidos por atacantes. | D16: Prueba en el navegador nombres habituales de shells sobre tu dominio. Cualquiera que devuelva algo distinto de un 404 es un problema. | E16: alta | F16: Sin comprobar
B17: ¿No hay PHP accesible en la carpeta de subidas? | C17: En /uploads no debería ejecutarse nada. | D17: Busca ficheros .php dentro de wp-content/uploads por FTP o por el gestor de archivos. No debería haber ninguno. | E17: alta | F17: Sin comprobar
B18: ¿Están cerrados install.php y los ficheros de instalación? | C18: Puerta de entrada para reinstalar por encima y quedarse con el sitio. | D18: Comprueba que tudominio.com/wp-admin/install.php no deja reinstalar nada. | E18: media | F18: Sin comprobar
B19: ¿Está inaccesible el repositorio .git? | C19: Un .git expuesto entrega el código fuente y a veces credenciales. | D19: Prueba tudominio.com/.git/config en el navegador. Si te descarga algo, estás entregando el código fuente y a veces credenciales. | E19: media | F19: Sin comprobar
B20: ¿No hay copias descargables en la raíz? | C20: Un .zip o .sql accesible es la base de datos entera al alcance de cualquiera. | D20: Prueba en el navegador los nombres típicos de copias en la raíz, con extensión .zip o .sql. Un fichero así accesible es tu base de datos entera al alcance de cualquiera. | E20: alta | F20: Sin comprobar
B21: ¿Está inaccesible debug.log? | C21: Suele filtrar rutas y a veces datos personales. | D21: Prueba tudominio.com/wp-content/debug.log. Suele filtrar rutas del servidor y a veces datos personales. | E21: media | F21: Sin comprobar
B22: ¿Está inaccesible el fichero .env? | C22: Si existe y es accesible, entrega credenciales en texto plano. | D22: Prueba tudominio.com/.env. Si existe y responde, estás entregando credenciales en texto plano. | E22: alta | F22: Sin comprobar
B23: ¿No hay clones o staging públicos? | C23: Una copia olvidada y sin actualizar es la vía de entrada perfecta. | D23: Busca clones olvidados en subdominios o subcarpetas del tipo /old, /dev o /copia. Una copia sin actualizar es la vía de entrada perfecta. | E23: media | F23: Sin comprobar
A24: Infraestructura | B24: ¿Los registros MX son los que deberían? | C24: Un MX cambiado significa correo secuestrado. | D24: Mira los registros MX de tu dominio con cualquier consultor de DNS. Un MX cambiado significa correo secuestrado. | E24: alta | F24: Sin comprobar
B25: ¿El SPF está bien y sin IPs ajenas? | C25: Un SPF que autoriza servidores que no son los tuyos es spam saliente firmado por tu propio dominio. | D25: Consulta el registro TXT del SPF. Si autoriza servidores que no son los tuyos, es spam saliente firmado por tu propio dominio. | E25: alta | F25: Sin comprobar
B26: ¿Hay DMARC publicado? | C26: Sin DMARC, cualquiera puede suplantar el dominio en el correo. | D26: Consulta el TXT de _dmarc.tudominio.com. Sin DMARC, cualquiera puede suplantarte en el correo. | E26: media | F26: Sin comprobar
B27: ¿Los subdominios con certificado son todos conocidos? | C27: Por Certificate Transparency aparecen subdominios creados por el atacante. | D27: En crt.sh, con el enlace de la hoja 4, salen los subdominios que han pedido certificado. Ahí aparecen los que creó el atacante. | E27: media | F27: Sin comprobar
B28: ¿Las cabeceras de seguridad están puestas? | C28: No detectan un compromiso, pero forman parte del endurecimiento posterior. | D28: Con el analizador de cabeceras de la hoja 4. No detectan un compromiso, pero forman parte de dejar la web mejor de como estaba. | E28: baja | F28: Sin comprobar
B29: ¿El certificado es válido y con la cadena completa? | C29: Un certificado roto tras el ataque suele indicar que se tocó la configuración del servidor. | D29: Con SSL Labs, en la hoja 4. Un certificado roto después del ataque suele querer decir que alguien tocó la configuración del servidor. | E29: media | F29: Sin comprobar
B30: ¿El servidor oculta su versión y la de PHP? | C30: Facilita al siguiente elegir el exploit adecuado. | D30: En las cabeceras de respuesta, mira si el servidor va publicando su versión y la de PHP. Le pone fácil al siguiente elegir con qué atacarte. | E30: baja | F30: Sin comprobar
A31: Reputación | B31: ¿La IP del servidor está en listas negras de correo? | C31: Si la IP de tu servidor está en una lista negra, tu correo deja de llegar a medio mundo. | D31: Con el enlace de Spamhaus o el de MxToolbox de la hoja 4. Si sale la IP de tu servidor, tu correo está rebotando en medio mundo. | E31: alta | F31: Sin comprobar

Sheet 4 Comprobaciones online
A1: Comprobaciones online
A2: Escribe tu dominio en la portada y los enlaces se montan solos. Guarda una captura de cada uno antes de limpiar: es la única forma de demostrar después que la web estaba mal y ya no lo está.
A4: Servicio | B4: Para qué sirve | C4: Cuándo se pasa | D4: Enlace | E4: Resultado | F4: Fecha | G4: Notas
A5: Análisis de seguridad de AyudaWP | B5: Cabeceras, exposición y configuración de un vistazo, sin instalar nada. Vale como foto del antes y del después. | C5: Antes y después | D5: =HYPERLINK("https://herramientas.ayudawp.com/security-check/","Abrir") -> Abrir | E5: Sin comprobar | G5: Pega tu dominio en la herramienta. Guarda captura.
A6: Cabeceras de seguridad de AyudaWP | B6: Para la parte de dejar la web mejor de como estaba, cuando ya esté limpia. | C6: Al terminar | D6: =HYPERLINK("https://herramientas.ayudawp.com/security-headers/","Abrir") -> Abrir | E6: Sin comprobar | G6: Pega tu dominio en la herramienta.
A7: Auditoría del tema | B7: Si sospechas del tema, o si estás decidiendo si lo cambias. | C7: Antes de limpiar | D7: =HYPERLINK("https://herramientas.ayudawp.com/theme-audit/","Abrir") -> Abrir | E7: Sin comprobar | G7: Pega tu dominio en la herramienta.
A8: Visibilidad para IA | B8: Después de un spam SEO, para ver cómo ha quedado la web de cara a los buscadores y a los modelos de IA. | C8: Al terminar | D8: =HYPERLINK("https://herramientas.ayudawp.com/ai-visibility/","Abrir") -> Abrir | E8: Sin comprobar | G8: Pega tu dominio en la herramienta.
A9: Límite de rastreo | B9: Cuántas URLs ve un rastreador en tu web. Delata las páginas basura que dejó el spam. | C9: Antes y después | D9: =HYPERLINK("https://herramientas.ayudawp.com/crawl-limit/","Abrir") -> Abrir | E9: Sin comprobar | G9: Pega tu dominio en la herramienta.
A10: Auditoría SEO de AyudaWP | B10: Después de un spam SEO, para ver cómo ha quedado la web y tener con qué compararla dentro de unas semanas. | C10: Al terminar | D10: =HYPERLINK("https://herramientas.ayudawp.com/auditoria-seo/","Abrir") -> Abrir | E10: Sin comprobar | G10: Pega tu dominio en la herramienta.
A11: Sucuri SiteCheck | B11: Escáner del que beben bastantes otros. Suele ser el que mira quien te avisa de que tu web está rara. | C11: Antes y después | D11: =IF(Portada!$C$6="","Escribe tu dominio en la portada",HYPERLINK(SUBSTITUTE("https://sitecheck.sucuri.net/results/{dominio}","{dominio}",Portada!$C$6),"Abrir")) -> Abrir | E11: Sin comprobar | G11: Guarda captura.
A12: VirusTotal | B12: Veredicto agregado de decenas de motores de antivirus. | C12: Antes y después | D12: =IF(Portada!$C$6="","Escribe tu dominio en la portada",HYPERLINK(SUBSTITUTE("https://www.virustotal.com/gui/domain/{dominio}","{dominio}",Portada!$C$6),"Abrir")) -> Abrir | E12: Sin comprobar | G12: Guarda captura.
A13: Informe de transparencia de Google | B13: Estado público del dominio en Safe Browsing. | C13: Antes y después | D13: =IF(Portada!$C$6="","Escribe tu dominio en la portada",HYPERLINK(SUBSTITUTE("https://transparencyreport.google.com/safe-browsing/search?url={dominio}","{dominio}",Portada!$C$6),"Abrir")) -> Abrir | E13: Sin comprobar | G13: Guarda captura.
A14: Norton Safe Web | B14: Reputación de Norton, que afecta a muchos antivirus de escritorio. | C14: Antes y después | D14: =IF(Portada!$C$6="","Escribe tu dominio en la portada",HYPERLINK(SUBSTITUTE("https://safeweb.norton.com/report/show?url={dominio}","{dominio}",Portada!$C$6),"Abrir")) -> Abrir | E14: Sin comprobar | G14: Guarda captura.
A15: Quttera | B15: Segunda opinión de malware, útil cuando SiteCheck no ve nada y todavía hay quien te dice que le salta un aviso. | C15: Antes y después | D15: =IF(Portada!$C$6="","Escribe tu dominio en la portada",HYPERLINK(SUBSTITUTE("https://quttera.com/sitescan/{dominio}","{dominio}",Portada!$C$6),"Abrir")) -> Abrir | E15: Sin comprobar | G15: Guarda captura.
A16: URLVoid | B16: Agregador de listas negras de reputación. | C16: Antes y después | D16: =IF(Portada!$C$6="","Escribe tu dominio en la portada",HYPERLINK(SUBSTITUTE("https://www.urlvoid.com/scan/{dominio}/","{dominio}",Portada!$C$6),"Abrir")) -> Abrir | E16: Sin comprobar | G16: Guarda captura.
A17: Spamhaus | B17: Listas negras de correo. Imprescindible si tu dominio ha estado enviando spam. | C17: Antes y después | D17: =IF(Portada!$C$6="","Escribe tu dominio en la portada",HYPERLINK(SUBSTITUTE("https://check.spamhaus.org/results/?query={dominio}","{dominio}",Portada!$C$6),"Abrir")) -> Abrir | E17: Sin comprobar | G17: Guarda captura.
A18: MxToolbox, listas negras | B18: Barrido de listas negras de correo de una vez. | C18: Antes y después | D18: =IF(Portada!$C$6="","Escribe tu dominio en la portada",HYPERLINK(SUBSTITUTE("https://mxtoolbox.com/SuperTool.aspx?action=blacklist%3a{dominio}","{dominio}",Portada!$C$6),"Abrir")) -> Abrir | E18: Sin comprobar | G18: Guarda captura.
A19: Google: páginas indexadas | B19: Cuántas páginas tiene indexadas y si hay basura entre ellas. | C19: Antes y después | D19: =IF(Portada!$C$6="","Escribe tu dominio en la portada",HYPERLINK(SUBSTITUTE("https://www.google.com/search?q=site%3A{dominio}","{dominio}",Portada!$C$6),"Abrir")) -> Abrir | E19: Sin comprobar | G19: Guarda captura.
A20: Google: spam indexado | B20: Delata el spam SEO en un vistazo. Si esto devuelve resultados, hay contenido inyectado indexado. | C20: Antes y después | D20: =IF(Portada!$C$6="","Escribe tu dominio en la portada",HYPERLINK(SUBSTITUTE("https://www.google.com/search?q=site%3A{dominio}+%28viagra+OR+casino+OR+cialis+OR+replica+OR+payday%29","{dominio}",Portada!$C$6),"Abrir")) -> Abrir | E20: Sin comprobar | G20: Guarda captura.
A21: SSL Labs | B21: Certificado y cadena de confianza. Se mira al final, cuando toca dejarlo todo mejor de como estaba. | C21: Al terminar | D21: =IF(Portada!$C$6="","Escribe tu dominio en la portada",HYPERLINK(SUBSTITUTE("https://www.ssllabs.com/ssltest/analyze.html?d={dominio}","{dominio}",Portada!$C$6),"Abrir")) -> Abrir | E21: Sin comprobar
A22: Security Headers | B22: Cabeceras de seguridad tras el endurecimiento. | C22: Al terminar | D22: =IF(Portada!$C$6="","Escribe tu dominio en la portada",HYPERLINK(SUBSTITUTE("https://securityheaders.com/?q={dominio}","{dominio}",Portada!$C$6),"Abrir")) -> Abrir | E22: Sin comprobar
A23: crt.sh | B23: Subdominios con certificado emitido, incluidos los que no debería haber. | C23: Antes de limpiar | D23: =IF(Portada!$C$6="","Escribe tu dominio en la portada",HYPERLINK(SUBSTITUTE("https://crt.sh/?q=%25.{dominio}","{dominio}",Portada!$C$6),"Abrir")) -> Abrir | E23: Sin comprobar
A24: Archive.org | B24: Cómo era tu web antes de todo esto. Sirve para fechar el ataque y para recuperar contenido que se haya perdido. | C24: Antes de limpiar | D24: =IF(Portada!$C$6="","Escribe tu dominio en la portada",HYPERLINK(SUBSTITUTE("https://web.archive.org/web/*/{dominio}","{dominio}",Portada!$C$6),"Abrir")) -> Abrir | E24: Sin comprobar

Sheet 5 Reputación y retiradas
A1: Reputación y retiradas
A2: Estar limpio y parecerlo son dos trabajos distintos. Esta parte va después de la limpieza, nunca antes, y se cuenta en días.
A4: Servicio | B4: Por qué importa | C4: Mirar | D4: Reclamar | E4: Cómo se pide la retirada | F4: Estado | G4: Fecha
A5: Google Safe Browsing | B5: Si Google tiene tu web marcada, que es lo que hace salir la pantalla roja en Chrome y el aviso en los resultados de búsqueda. | C5: =IF(Portada!$C$6="","Escribe tu dominio en la portada",HYPERLINK(SUBSTITUTE("https://transparencyreport.google.com/safe-browsing/search?url={dominio}","{dominio}",Portada!$C$6),"Mirar")) -> Mirar | D5: =HYPERLINK("https://search.google.com/search-console/security-issues","Reclamar") -> Reclamar | E5: La retirada se pide en Search Console, en Problemas de seguridad, y solo con la web ya limpia. Un intento gastado con la web todavía sucia alarga la espera. | F5: Pendiente
A6: Listas negras de correo (DNSBL) | B6: Si la IP de tu servidor está en Spamhaus, Barracuda o SpamCop, tu correo rebota en medio mundo. | C6: =IF(Portada!$C$6="","Escribe tu dominio en la portada",HYPERLINK(SUBSTITUTE("https://check.spamhaus.org/results/?query={dominio}","{dominio}",Portada!$C$6),"Mirar")) -> Mirar | D6: =HYPERLINK("https://check.spamhaus.org/","Reclamar") -> Reclamar | E6: Cortar primero el envío de spam. Si se pide la salida con el servidor todavía enviando, se vuelve a entrar al día siguiente y la segunda vez cuesta más. | F6: Pendiente
A7: Google Search Console | B7: Fuente autoritativa del aviso de Google y única vía oficial para pedir la revisión. | C7: =HYPERLINK("https://search.google.com/search-console/security-issues","Mirar") -> Mirar | D7: =HYPERLINK("https://search.google.com/search-console/security-issues","Reclamar") -> Reclamar | E7: Problemas de seguridad, revisar el detalle, arreglar todo, y solicitar revisión. La respuesta suele tardar de horas a días. Anotar la fecha de solicitud. | F7: Pendiente
A8: Bing Webmaster Tools | B8: Equivalente de Bing, que alimenta a otros buscadores y a algunos antivirus. | C8: =HYPERLINK("https://www.bing.com/webmasters/","Mirar") -> Mirar | D8: =HYPERLINK("https://www.bing.com/webmasters/","Reclamar") -> Reclamar | E8: Sección de seguridad de la propiedad, solicitud de revisión. | F8: Pendiente
A9: Sucuri SiteCheck | B9: Escáner público de referencia. Guarda la captura del antes y la del después. | C9: En la hoja 4 | D9: =HYPERLINK("https://sitecheck.sucuri.net/","Reclamar") -> Reclamar | E9: Se actualiza volviendo a escanear. Si sigue marcando algo tras la limpieza, es que queda algo: mirarlo antes de discutir con nadie. | F9: Pendiente
A10: VirusTotal | B10: Veredicto agregado de decenas de motores. Guarda la captura de cómo estaba y de cómo queda. | C10: En la hoja 4 | D10: =HYPERLINK("https://support.virustotal.com/hc/en-us/articles/115002146549-False-positives","Reclamar") -> Reclamar | E10: Cada motor que marque tiene su propio proceso. Empezar por los que aparezcan en rojo en la ficha del dominio. | F10: Pendiente
A11: Norton Safe Web | B11: Reputación que arrastran muchos antivirus de escritorio. | C11: En la hoja 4 | D11: =HYPERLINK("https://safeweb.norton.com/help/site_owners","Reclamar") -> Reclamar | E11: Solicitud de revisión desde la ficha del sitio, con la web ya limpia. | F11: Pendiente
A12: Hosting | B12: Si suspendió o limitó la cuenta, hay que pedir la reactivación con el detalle de lo hecho. | C12: Tu panel o tus tickets | E12: Abre un ticket con el resumen de la limpieza: qué encontraste, qué eliminaste y qué medidas has dejado puestas. | F12: Pendiente
A13: Pasarela de pago | B13: Si avisó la pasarela o el banco, hay que responder por escrito. | C13: El correo de tu pasarela | E13: Responde por escrito con lo corregido y las medidas puestas. Si hubo datos de pago afectados, esto va de la mano de lo de la brecha. | F13: Pendiente

Sheet 6 Patrones de código
A1: Patrones de código que conviene buscar
A2: Son indicios y no sentencias, porque el PHP legítimo también usa base64 o eval de vez en cuando. Cada coincidencia se mira con su ruta y su contexto antes de decidir nada. Antes de borrar un fichero, ábrelo y mira qué hace.
A3: Con SSH: grep -rEn --include="*.php" "PATRÓN" /ruta/de/tu/web · Sin SSH, el buscador del gestor de archivos del hosting también sirve, aunque tendrás que ir uno por uno.
A5: Qué buscar | B5: Qué significa si aparece | C5: Gravedad | D5: ¿Lo encuentras? | E5: Dónde (rutas)
A6: eval\s*\(\s*base64_decode | B6: Ejecutar código codificado en base64. Es la firma clásica de puerta trasera. | C6: alta | D6: Sin comprobar
A7: eval\s*\(\s*gzinflate | B7: Código comprimido que se ejecuta al vuelo, para esquivar búsquedas. | C7: alta | D7: Sin comprobar
A8: gzinflate\s*\(\s*str_rot13 | B8: Doble ofuscación. En código legítimo no se ve nunca. | C8: alta | D8: Sin comprobar
A9: preg_replace\s*\(\s*['\"][^'\"]*['\"]e | B9: Modificador /e de preg_replace: ejecuta código. Retirado de PHP hace años y típico de shells viejos. | C9: alta | D9: Sin comprobar
A10: assert\s*\(\s*\$ | B10: assert con variable, otra forma de ejecutar código dinámico. | C10: media | D10: Sin comprobar
A11: create_function\s*\( | B11: Función eliminada de PHP 8. En una web actual, o es código muy viejo o es malware. | C11: media | D11: Sin comprobar
A12: \$_(POST|GET|REQUEST|COOKIE)\s*\[[^\]]*\]\s*\)?\s*\( | B12: Ejecuta directamente lo que llega por la petición. Puerta trasera de manual. | C12: alta | D12: Sin comprobar
A13: (shell_exec|passthru|popen|proc_open)\s*\( | B13: Ejecución de comandos del sistema. En un plugin normal no pinta nada. | C13: media | D13: Sin comprobar
A14: \b(system|exec)\s*\(\s*\$ | B14: Comando del sistema construido con una variable. | C14: media | D14: Sin comprobar
A15: (FilesMan|WSO |b374k|IndoXploit|Mini Shell|c99shell|r57shell) | B15: Nombres de shells web conocidos. | C15: alta | D15: Sin comprobar
A16: \\x[0-9a-fA-F]{2}(\\x[0-9a-fA-F]{2}){20,} | B16: Cadena hexadecimal larga, forma habitual de esconder texto. | C16: media | D16: Sin comprobar
A17: ['\"][A-Za-z0-9+/]{300,}={0,2}['\"] | B17: Base64 muy largo dentro del código. A veces es una imagen; a veces es la carga útil. | C17: baja | D17: Sin comprobar
... A25: <iframe[^>]*(display\s*:\s*none|width\s*=\s*['\"]?[01]['\"]?) | B25: Iframe invisible, clásico para distribuir malware. | C25: alta | D25: Sin comprobar

Sheet 7 No volver a pasar
A1: Para que no vuelva a pasar
A2: Una limpieza es una foto fija. Lo que sostiene una web en pie es lo de abajo, y casi todo se hace una vez.
A4: Medida | B4: Por qué | C4: Estado | D4: Notas
A5: Doble factor para todos los administradores | B5: Es la medida que más ataques evita por lo poco que cuesta. Con la contraseña sola no basta, porque las contraseñas se filtran en sitios que no controlas. | C5: Pendiente
A6: Revisar quién tiene acceso y con qué rol | B6: Casi todas las webs arrastran usuarios de gente que ya no trabaja allí. Cada uno es una puerta más. | C6: Pendiente
A7: Contraseñas únicas y un gestor de contraseñas | B7: Reutilizar la contraseña del correo en la web significa que una filtración ajena se convierte en un problema propio. | C7: Pendiente
A8: Actualizaciones al día, con copia previa | B8: La mayoría de los ataques entran por agujeros ya parcheados. No es que sean listos, es que la web iba atrasada. | C8: Pendiente | D8: =HYPERLINK("https://mantenimiento.ayudawp.com","https://mantenimiento.ayudawp.com") -> https://mantenimiento.ayudawp.com
A9: Copias 3-2-1 y probar la restauración | B9: Una copia que nunca se ha restaurado no sirve. Es el punto donde falla casi todo el mundo. | C9: Pendiente
A10: Nada de plugins ni temas nulled | B10: El que los publica gratis no lo hace por amor al arte: los distribuye con la puerta trasera dentro. Es la vía de entrada más común que hay. | C10: Pendiente
A11: Equipos limpios de quien administra la web | B11: Si hay un troyano en el portátil que roba contraseñas, la web se vuelve a infectar por muy bien que se limpie. | C11: Pendiente
A12: Hosting con aislamiento entre sitios | B12: En muchos compartidos, una web infectada contamina a las demás de la misma cuenta. | C12: Pendiente
A13: Cortafuegos o Cloudflare por delante | B13: Filtra buena parte del ruido antes de que llegue a WordPress y frena los ataques de fuerza bruta. | C13: Pendiente
A14: Vigilancia continua de ficheros y vulnerabilidades | B14: Lo que se detecta en horas se arregla en horas. Lo que se detecta cuando Google te marca en rojo, cuesta semanas de reputación. | C14: Pendiente | D14: =HYPERLINK("https://vigilante.works/","https://vigilante.works/") -> https://vigilante.works/
